[
    {
        "Object Name": "ground_plane",
        "Object Pose": {
            "position": {
                "x": 0.0,
                "y": 0.0,
                "z": 0.0
            },
            "orientation": {
                "x": 0.0,
                "y": 0.0,
                "z": 0.0,
                "w": 1.0
            }
        }
    },
    {
        "Object Name": "wall_1_model",
        "Object Pose": {
            "position": {
                "x": 0.0,
                "y": -13.0,
                "z": 1.0
            },
            "orientation": {
                "x": 0.0,
                "y": 0.0,
                "z": 0.0,
                "w": 1.0
            }
        }
    },
    {
        "Object Name": "wall_2_model",
        "Object Pose": {
            "position": {
                "x": 0.0,
                "y": 2.0,
                "z": 1.0
            },
            "orientation": {
                "x": 0.0,
                "y": 0.0,
                "z": 0.0,
                "w": 1.0
            }
        }
    },
    {
        "Object Name": "wall_3_model",
        "Object Pose": {
            "position": {
                "x": -5.0,
                "y": -5.5,
                "z": 1.0
            },
            "orientation": {
                "x": 0.0,
                "y": 0.0,
                "z": 0.0,
                "w": 1.0
            }
        }
    },
    {
        "Object Name": "wall_4_model",
        "Object Pose": {
            "position": {
                "x": 5.0,
                "y": -5.5,
                "z": 1.0
            },
            "orientation": {
                "x": 0.0,
                "y": 0.0,
                "z": 0.0,
                "w": 1.0
            }
        }
    },
    {
        "Object Name": "wall_5_model",
        "Object Pose": {
            "position": {
                "x": -2.25,
                "y": -3.0,
                "z": 1.0
            },
            "orientation": {
                "x": 0.0,
                "y": 0.0,
                "z": 0.0,
                "w": 1.0
            }
        }
    },
    {
        "Object Name": "wall_6_model",
        "Object Pose": {
            "position": {
                "x": 3.75,
                "y": -3.0,
                "z": 1.0
            },
            "orientation": {
                "x": 0.0,
                "y": 0.0,
                "z": 0.0,
                "w": 1.0
            }
        }
    },
    {
        "Object Name": "cabinet",
        "Object Pose": {
            "position": {
                "x": 1.9999866012787195,
                "y": 0.9999688676107721,
                "z": -3.649346478340476e-07
            },
            "orientation": {
                "x": 8.148301229736712e-07,
                "y": -8.436086702960268e-08,
                "z": 3.338443747390629e-05,
                "w": 0.9999999994424041
            }
        }
    },
    {
        "Object Name": "cabinet_0",
        "Object Pose": {
            "position": {
                "x": 2.5157271918072754,
                "y": -5.439491883170183,
                "z": 1.1125416810031652e-08
            },
            "orientation": {
                "x": -7.424332879768265e-08,
                "y": 4.584459824073086e-07,
                "z": 0.00045549193562649347,
                "w": 0.999999896263435
            }
        }
    },
    {
        "Object Name": "bookshelf",
        "Object Pose": {
            "position": {
                "x": 2.000000000030189,
                "y": -9.554009999985338,
                "z": 5.452280557924188e-07
            },
            "orientation": {
                "x": -2.7261884088839743e-05,
                "y": -2.0411428798097526e-13,
                "z": 2.2107001876229068e-11,
                "w": 0.9999999996283949
            }
        }
    },
    {
        "Object Name": "bookshelf_0",
        "Object Pose": {
            "position": {
                "x": -2.4965699999669995,
                "y": -1.5789399999811076,
                "z": 5.809596471904319e-07
            },
            "orientation": {
                "x": -2.904846366321488e-05,
                "y": -2.0413418643543855e-13,
                "z": 2.143236777003942e-11,
                "w": 0.9999999995780934
            }
        }
    },
    {
        "Object Name": "bookshelf_1",
        "Object Pose": {
            "position": {
                "x": -2.4981599999669992,
                "y": 1.4678500000188885,
                "z": 5.80893814687672e-07
            },
            "orientation": {
                "x": -2.90451720375798e-05,
                "y": -2.0413413332459684e-13,
                "z": 2.1432895731620147e-11,
                "w": 0.9999999995781891
            }
        }
    },
    {
        "Object Name": "table",
        "Object Pose": {
            "position": {
                "x": -1.0000000194639513,
                "y": -8.999995790185265,
                "z": -0.1000048824503053
            },
            "orientation": {
                "x": -6.310205241529442e-07,
                "y": -3.244831952180441e-06,
                "z": -5.784403311293838e-06,
                "w": 0.9999999999778069
            }
        }
    },
    {
        "Object Name": "cabinet_1",
        "Object Pose": {
            "position": {
                "x": -3.0000028081927286,
                "y": -4.400051883170179,
                "z": 1.1125416810031652e-08
            },
            "orientation": {
                "x": -7.424332890322305e-08,
                "y": 4.584459824272821e-07,
                "z": 0.0004554919356121712,
                "w": 0.9999998962634352
            }
        }
    },
    {
        "Object Name": "cabinet_2",
        "Object Pose": {
            "position": {
                "x": -1.4918328081927283,
                "y": -4.456221883170206,
                "z": 1.1125416810031652e-08
            },
            "orientation": {
                "x": -7.424332889486141e-08,
                "y": 4.5844598247763385e-07,
                "z": 0.00045549193559768557,
                "w": 0.9999998962634351
            }
        }
    },
    {
        "Object Name": "bookshelf_2",
        "Object Pose": {
            "position": {
                "x": -3.4184899999669973,
                "y": -6.999999999981115,
                "z": 5.81054117055601e-07
            },
            "orientation": {
                "x": -2.905318715755524e-05,
                "y": -2.041342652912071e-13,
                "z": 2.1431609226169745e-11,
                "w": 0.9999999995779563
            }
        }
    },
    {
        "Object Name": "table_0",
        "Object Pose": {
            "position": {
                "x": -1.0000537029992618,
                "y": -6.9997156274075785,
                "z": -0.1195728531577419
            },
            "orientation": {
                "x": -0.0009568395049814614,
                "y": -0.0007168802352305955,
                "z": 5.193732709415444e-06,
                "w": 0.9999992852567023
            }
        }
    },
    {
        "Object Name": "table_1",
        "Object Pose": {
            "position": {
                "x": -1.0000000194639513,
                "y": -10.999995790185265,
                "z": -0.1000048824503053
            },
            "orientation": {
                "x": -6.310205241529442e-07,
                "y": -3.244831952180441e-06,
                "z": -5.784403311293838e-06,
                "w": 0.9999999999778069
            }
        }
    },
    {
        "Object Name": "cabinet_3",
        "Object Pose": {
            "position": {
                "x": 2.9999971918072914,
                "y": -1.0000018831701616,
                "z": 1.1125416587987047e-08
            },
            "orientation": {
                "x": -7.424332880000369e-08,
                "y": 4.5844598244570605e-07,
                "z": 0.0004554919356737842,
                "w": 0.9999998962634351
            }
        }
    },
    {
        "Object Name": "bookshelf_3",
        "Object Pose": {
            "position": {
                "x": 2.450550000023169,
                "y": -11.999999999971719,
                "z": 5.455287676370396e-07
            },
            "orientation": {
                "x": -2.727691968785265e-05,
                "y": -2.0397214949091485e-13,
                "z": 1.6883864143851993e-11,
                "w": 0.9999999996279849
            }
        }
    },
    {
        "Object Name": "bookshelf_4",
        "Object Pose": {
            "position": {
                "x": 2.5131600000198726,
                "y": -7.99999999997677,
                "z": 5.426821641398265e-07
            },
            "orientation": {
                "x": -2.7134589512716364e-05,
                "y": -2.042177485420067e-13,
                "z": 2.602359882189469e-11,
                "w": 0.9999999996318572
            }
        }
    },
    {
        "Object Name": "bookshelf_5",
        "Object Pose": {
            "position": {
                "x": -3.5392899999698115,
                "y": -10.422219999985334,
                "z": 5.452368280631606e-07
            },
            "orientation": {
                "x": -2.726232270330843e-05,
                "y": -2.0411430971947048e-13,
                "z": 2.2107447517059494e-11,
                "w": 0.9999999996283829
            }
        }
    },
    {
        "Object Name": "bookshelf_6",
        "Object Pose": {
            "position": {
                "x": -3.999999999976242,
                "y": -5.474649999990038,
                "z": 8.959815531739338e-08
            },
            "orientation": {
                "x": -4.480389058752721e-06,
                "y": 2.0342826833546855e-13,
                "z": 1.86012206471647e-11,
                "w": 0.999999999989963
            }
        }
    },
    {
        "Object Name": "cabinet_4",
        "Object Pose": {
            "position": {
                "x": -0.5369609567739889,
                "y": -2.0000295151064833,
                "z": -1.0490812360153257e-05
            },
            "orientation": {
                "x": 9.37812183610311e-08,
                "y": 9.097966075251246e-07,
                "z": 7.946389061514856e-05,
                "w": 0.9999999968423268
            }
        }
    },
    {
        "Object Name": "beer",
        "Object Pose": {
            "position": {
                "x": -1.1547664812556317,
                "y": -6.79400091426115,
                "z": 0.7948119900109764
            },
            "orientation": {
                "x": -0.0010492749628406425,
                "y": -0.0008264203916888606,
                "z": -0.009001768516671591,
                "w": 0.9999585912501382
            }
        },
        "Expected Location": "cafe_table",
        "Current Location": "table"
    },
    {
        "Object Name": "coke_can",
        "Object Pose": {
            "position": {
                "x": 2.0000374395638447,
                "y": 0.9999561343962143,
                "z": 1.0174250061559378
            },
            "orientation": {
                "x": -0.005635779355148819,
                "y": 0.0018919622903763795,
                "z": 0.01143356691635778,
                "w": 0.9999169625610523
            }
        },
        "Expected Location": "cafe_table",
        "Current Location": "table"
    },
    {
        "Object Name": "Juice",
        "Object Pose": {
            "position": {
                "x": -0.5000042295746373,
                "y": -1.999981042237206,
                "z": 1.0174230155512352
            },
            "orientation": {
                "x": -0.005571960640942078,
                "y": 0.0020591414730777332,
                "z": -0.009835910816846798,
                "w": 0.999933981845508
            }
        }
    },
    {
        "Object Name": "tiago",
        "Object Pose": {
            "position": {
                "x": 0.48574352901328316,
                "y": -12.001942117698102,
                "z": -0.0015440709571384048
            },
            "orientation": {
                "x": 0.00012499424167597807,
                "y": 0.0005716882801774189,
                "z": 0.7166995795875604,
                "w": 0.6973817965562079
            }
        }
    }
]